pylitedb/__init__.py
pylitedb/common/types.py
pylitedb/db/database.py
pylitedb/db/table.py
pylitedb-1.0.5.dist-info/LICENSE.txt
pylitedb-1.0.5.dist-info/METADATA
pylitedb-1.0.5.dist-info/WHEEL
pylitedb-1.0.5.dist-info/top_level.txt
pylitedb-1.0.5.dist-info/RECORD
