Metadata-Version: 2.1
Name: pylitedb
Version: 1.0.5
Summary: Very Simple helper classes for managing sqlite databases
Author-email: Philippe Lacroix-Ouellette <philippe.lacroix.ouellette@gmail.com>
License: MIT License
Project-URL: Homepage, https://github.com/phil-lo/dblite
Keywords: sqlite,sqlite3,utilities
Classifier: License :: OSI Approved :: MIT License
Classifier: Programming Language :: Python
Classifier: Programming Language :: Python :: 3
Requires-Python: >=3.9
License-File: LICENSE.txt
Requires-Dist: sqlite-utils (>=3.30)
Provides-Extra: dev
